aliyunsdkemas_appmonitor/__init__.py
aliyunsdkemas_appmonitor/endpoint.py
aliyunsdkemas_appmonitor/request/__init__.py
aliyunsdkemas_appmonitor/request/v20190611/GetAlarmLogRequest.py
aliyunsdkemas_appmonitor/request/v20190611/GetAppDailyDeviceCountRequest.py
aliyunsdkemas_appmonitor/request/v20190611/GetAppFilePolicyRequest.py
aliyunsdkemas_appmonitor/request/v20190611/GetAppMonthlyDeviceCountRequest.py
aliyunsdkemas_appmonitor/request/v20190611/GetAppStatusRequest.py
aliyunsdkemas_appmonitor/request/v20190611/GetCrashSummaryRequest.py
aliyunsdkemas_appmonitor/request/v20190611/GetSdkConfigRequest.py
aliyunsdkemas_appmonitor/request/v20190611/QueryApiAvgDurationGroupTrendRequest.py
aliyunsdkemas_appmonitor/request/v20190611/QueryApiAvgDurationTrendRequest.py
aliyunsdkemas_appmonitor/request/v20190611/QueryApiDurationDistributionRequest.py
aliyunsdkemas_appmonitor/request/v20190611/QueryApiErrorGroupTrendRequest.py
aliyunsdkemas_appmonitor/request/v20190611/QueryApiErrorTrendRequest.py
aliyunsdkemas_appmonitor/request/v20190611/QueryApiStatusCodeGroupTrendRequest.py
aliyunsdkemas_appmonitor/request/v20190611/QueryApiStatusCodeTrendRequest.py
aliyunsdkemas_appmonitor/request/v20190611/QueryCrashTrendRequest.py
aliyunsdkemas_appmonitor/request/v20190611/QueryLaunchTimeDistributionRequest.py
aliyunsdkemas_appmonitor/request/v20190611/QueryLaunchTimeTrendGroupByProvinceRequest.py
aliyunsdkemas_appmonitor/request/v20190611/QueryLaunchTimeTrendRequest.py
aliyunsdkemas_appmonitor/request/v20190611/QueryLaunchTimeTrendWithCarrierRequest.py
aliyunsdkemas_appmonitor/request/v20190611/QueryPagePerfDistributionRequest.py
aliyunsdkemas_appmonitor/request/v20190611/QueryPagePerfTrendGroupByPageNameRequest.py
aliyunsdkemas_appmonitor/request/v20190611/QueryPagePerfTrendGroupByProvinceRequest.py
aliyunsdkemas_appmonitor/request/v20190611/QueryPagePerfTrendRequest.py
aliyunsdkemas_appmonitor/request/v20190611/QuerySingleDomainApiAvgDurationGroupTrendRequest.py
aliyun_python_sdk_emas_appmonitor-1.2.0.dist-info/LICENSE
aliyun_python_sdk_emas_appmonitor-1.2.0.dist-info/METADATA
aliyun_python_sdk_emas_appmonitor-1.2.0.dist-info/WHEEL
aliyun_python_sdk_emas_appmonitor-1.2.0.dist-info/top_level.txt
aliyun_python_sdk_emas_appmonitor-1.2.0.dist-info/RECORD
